


[

  
      {
        "name": "Allie Budden",
        "email": "abudden0@ovh.net",
        "gender": "Female",
        "password": "QSaEWD"
      }, {
        "name": "Grant Evetts",
        "email": "gevetts1@mac.com",
        "gender": "Male",
        "password": "oMMm4nwJj"
      }, {
        "name": "Quentin Beeho",
        "email": "qbeeho2@ucsd.edu",
        "gender": "Male",
        "password": "17ptK25"
      }, {
        "name": "Kristian Pyer",
        "email": "kpyer3@naver.com",
        "gender": "Male",
        "password": "RbdFPxCCs"
      }, {
        "name": "Lorilee Colquhoun",
        "email": "lcolquhoun4@fc2.com",
        "gender": "Female",
        "password": "ZT1ElmDtqUIt"
      }, {
        "name": "Willem Clulow",
        "email": "wclulow5@state.gov",
        "gender": "Male",
        "password": "fWJytZ"
      }, {
        "name": "Bev Bauman",
        "email": "bbauman6@infoseek.co.jp",
        "gender": "Male",
        "password": "bEPoXKBLrM"
      }, {
        "name": "Gaven Bartoloma",
        "email": "gbartoloma7@marriott.com",
        "gender": "Male",
        "password": "KruNBcqro"
      }, {
        "name": "Gray Elland",
        "email": "gelland8@google.com",
        "gender": "Female",
        "password": "ZU9iDJuXj8"
      }, {
        "name": "Raffarty Najera",
        "email": "rnajera9@gravatar.com",
        "gender": "Male",
        "password": "AoMsx4JxNZb"
      }
  ]

  